restful_redis/__init__.py
restful_redis/client.py
restful_redis/definitions.py
restful_redis/exps.py
restful_redis/helpers.py
restful_redis/server.py
restful_redis-0.0.2.dist-info/DESCRIPTION.rst
restful_redis-0.0.2.dist-info/METADATA
restful_redis-0.0.2.dist-info/RECORD
restful_redis-0.0.2.dist-info/WHEEL
restful_redis-0.0.2.dist-info/metadata.json
restful_redis-0.0.2.dist-info/top_level.txt
