Metadata-Version: 2.0
Name: restful-redis
Version: 0.0.2
Summary: Redis queues for synchronous server2server ops
Home-page: https://github.com/whittlbc/restful_redis
Author: Ben Whittle
Author-email: benwhittle31@gmail.com
License: MIT.
Platform: UNKNOWN
Requires-Dist: redis (==2.10.6)
